<?xml version="1.0" encoding="UTF-8"?>
<!--
    Import pipeline for metadata from CAF.
-->
<beans xmlns="http://www.springframework.org/schema/beans" xmlns:xsi="http://www.w3.org/2001/XMLSchema-instance"
    xsi:schemaLocation="http://www.springframework.org/schema/beans http://www.springframework.org/schema/beans/spring-beans-3.0.xsd"> 

    <!--
        Import commonly used beans.
    -->
    <import resource="../common-beans.xml"/>
        
    <!--
        Import CAF-specific beans.
    -->
    <import resource="beans.xml"/>
    
    <bean id="caf.serializeImported" class="net.shibboleth.metadata.pipeline.SerializationStage"
        init-method="initialize" lazy-init="true">
        <property name="id" value="caf.serializeImported"/>
        <property name="serializer" ref="serializer"/>
        <property name="outputFile">
            <bean class="java.io.File">
                <constructor-arg value="#{ systemProperties['basedir'] }/mdx/caf/imported.xml"/>
            </bean>
        </property>
    </bean>
    
    <bean id="caf.import" class="net.shibboleth.metadata.pipeline.SimplePipeline"
        init-method="initialize" lazy-init="true">
        <property name="id" value="pipeline"/>
        <property name="stages">
            <list>
                <ref bean="fetchCafExportAggregate"/>
                <ref bean="checkCafSignature"/>
                
                <!-- failure to validate signature is fatal -->
                <ref bean="errorTerminatingFilter"/>
                
                <ref bean="disassemble"/>
                
                <ref bean="standardImportActions"/>
                
                <ref bean="standardImportTail"/>
                
                <ref bean="caf.serializeImported"/>
            </list>
        </property>
    </bean>
    
</beans>
